{
  "date": "2026-04-10",
  "date_id": "20260410",
  "last_updated": "2026-04-12 05:34:11",
  "source": "20260410.csv",
  "total_picks": 15,
  "stats": {
    "total_stocks": 2708,
    "filtered_stocks": 53,
    "final_picks": 15
  },
  "picks": [
    {
      "code": "7113",
      "name": "TOPGLOV",
      "price": 0.805,
      "volume": 729904,
      "b_percent": 61.0,
      "rsi": 50,
      "macd": 0.052,
      "sector_code": "162",
      "sector_name": "Industrial & Consumer Products",
      "total_score": 96,
      "vol_ratio": 0.01,
      "daily_change": 0.015,
      "reasons": "B% 61.0%; RSI中性; MACD金叉; 涨1.5%",
      "risk_label": "🔥強烈買入",
      "risk": "低"
    },
    {
      "code": "0245",
      "name": "MNHLDG",
      "price": 1.92,
      "volume": 71303,
      "b_percent": 57.0,
      "rsi": 50,
      "macd": 0.051,
      "sector_code": "403",
      "sector_name": "Property",
      "total_score": 95,
      "vol_ratio": 0.01,
      "daily_change": 0.06,
      "reasons": "B% 57.0%; RSI中性; MACD金叉; 大涨6.0%",
      "risk_label": "🔥強烈買入",
      "risk": "低"
    },
    {
      "code": "4677",
      "name": "YTL",
      "price": 1.99,
      "volume": 177002,
      "b_percent": 59.0,
      "rsi": 50,
      "macd": 0.019,
      "sector_code": "165",
      "sector_name": "Industrial & Consumer Products",
      "total_score": 95,
      "vol_ratio": 0.01,
      "daily_change": 0.05,
      "reasons": "B% 59.0%; RSI中性; MACD金叉; 大涨5.0%",
      "risk_label": "🔥強烈買入",
      "risk": "低"
    },
    {
      "code": "0652QW",
      "name": "HSI-CWQW",
      "price": 0.63,
      "volume": 97000,
      "b_percent": 56.0,
      "rsi": 50,
      "macd": 0.0,
      "sector_code": "358",
      "sector_name": "Technology",
      "total_score": 95,
      "vol_ratio": 1.0,
      "daily_change": 0.035,
      "reasons": "B% 56.0%; RSI中性; 大涨3.5%",
      "risk_label": "🔥強烈買入",
      "risk": "低"
    },
    {
      "code": "5243",
      "name": "VELESTO",
      "price": 0.345,
      "volume": 288120,
      "b_percent": 53.0,
      "rsi": 50,
      "macd": 0.008,
      "sector_code": "161",
      "sector_name": "Industrial & Consumer Products",
      "total_score": 93,
      "vol_ratio": 0.01,
      "daily_change": -0.005,
      "reasons": "B% 53.0%; RSI中性; MACD金叉",
      "risk_label": "🔥強烈買入",
      "risk": "低"
    },
    {
      "code": "5210",
      "name": "ARMADA",
      "price": 0.38,
      "volume": 288509,
      "b_percent": 58.0,
      "rsi": 50,
      "macd": 0.009,
      "sector_code": "161",
      "sector_name": "Industrial & Consumer Products",
      "total_score": 93,
      "vol_ratio": 0.01,
      "daily_change": 0.005,
      "reasons": "B% 58.0%; RSI中性; MACD金叉",
      "risk_label": "🔥強烈買入",
      "risk": "低"
    },
    {
      "code": "7106",
      "name": "SUPERMX",
      "price": 0.335,
      "volume": 161774,
      "b_percent": 57.0,
      "rsi": 50,
      "macd": 0.012,
      "sector_code": "162",
      "sector_name": "Industrial & Consumer Products",
      "total_score": 93,
      "vol_ratio": 0.01,
      "daily_change": 0.0,
      "reasons": "B% 57.0%; RSI中性; MACD金叉",
      "risk_label": "🔥強烈買入",
      "risk": "低"
    },
    {
      "code": "5168",
      "name": "HARTA",
      "price": 1.25,
      "volume": 166216,
      "b_percent": 60.0,
      "rsi": 50,
      "macd": 0.071,
      "sector_code": "162",
      "sector_name": "Industrial & Consumer Products",
      "total_score": 93,
      "vol_ratio": 0.01,
      "daily_change": 0.03,
      "reasons": "B% 60.0%; RSI中性; MACD金叉; 涨3.0%",
      "risk_label": "🔥強烈買入",
      "risk": "低"
    },
    {
      "code": "0024",
      "name": "JAG",
      "price": 0.335,
      "volume": 92498,
      "b_percent": 73.0,
      "rsi": 50,
      "macd": 0.001,
      "sector_code": "402",
      "sector_name": "Property",
      "total_score": 93,
      "vol_ratio": 0.01,
      "daily_change": -0.005,
      "reasons": "B% 73.0%; RSI中性; MACD金叉",
      "risk_label": "🔥強烈買入",
      "risk": "低"
    },
    {
      "code": "0391",
      "name": "AMBEST",
      "price": 0.425,
      "volume": 75248,
      "b_percent": 51.0,
      "rsi": 50,
      "macd": 0.029,
      "sector_code": "402",
      "sector_name": "Property",
      "total_score": 93,
      "vol_ratio": 0.01,
      "daily_change": 0.0,
      "reasons": "B% 51.0%; RSI中性; MACD金叉",
      "risk_label": "🔥強烈買入",
      "risk": "低"
    },
    {
      "code": "6742",
      "name": "YTLPOWR",
      "price": 3.7,
      "volume": 184552,
      "b_percent": 56.0,
      "rsi": 50,
      "macd": 0.166,
      "sector_code": "165",
      "sector_name": "Industrial & Consumer Products",
      "total_score": 91,
      "vol_ratio": 0.02,
      "daily_change": 0.1,
      "reasons": "B% 56.0%; RSI中性; MACD金叉; 大涨10.0%",
      "risk_label": "🔥強烈買入",
      "risk": "低"
    },
    {
      "code": "8869",
      "name": "PMETAL",
      "price": 7.9,
      "volume": 82961,
      "b_percent": 72.0,
      "rsi": 50,
      "macd": 0.1,
      "sector_code": "102",
      "sector_name": "Industrial & Consumer Products",
      "total_score": 91,
      "vol_ratio": 0.01,
      "daily_change": 0.04,
      "reasons": "B% 72.0%; RSI中性; MACD金叉; 大涨4.0%",
      "risk_label": "🔥強烈買入",
      "risk": "低"
    },
    {
      "code": "5249",
      "name": "IOIPG",
      "price": 3.63,
      "volume": 96695,
      "b_percent": 72.0,
      "rsi": 50,
      "macd": 0.009,
      "sector_code": "120",
      "sector_name": "Industrial & Consumer Products",
      "total_score": 91,
      "vol_ratio": 0.02,
      "daily_change": 0.21,
      "reasons": "B% 72.0%; RSI中性; MACD金叉; 大涨21.0%",
      "risk_label": "🔥強烈買入",
      "risk": "低"
    },
    {
      "code": "7153",
      "name": "KOSSAN",
      "price": 1.19,
      "volume": 60335,
      "b_percent": 65.0,
      "rsi": 50,
      "macd": 0.042,
      "sector_code": "162",
      "sector_name": "Industrial & Consumer Products",
      "total_score": 90,
      "vol_ratio": 0.01,
      "daily_change": 0.0,
      "reasons": "B% 65.0%; RSI中性; MACD金叉",
      "risk_label": "🔥強烈買入",
      "risk": "低"
    },
    {
      "code": "524945",
      "name": "IOIPG-C45",
      "price": 0.305,
      "volume": 75771,
      "b_percent": 64.0,
      "rsi": 50,
      "macd": 0.0,
      "sector_code": "320",
      "sector_name": "Technology",
      "total_score": 90,
      "vol_ratio": 0.03,
      "daily_change": 0.065,
      "reasons": "B% 64.0%; RSI中性; 大涨6.5%",
      "risk_label": "🔥強烈買入",
      "risk": "低"
    }
  ]
}